{
  "pods": [
    {
      "namespace": "default",
      "name": "pod-1",
      "metrics": {
        "containers": [
          {
            "name": "container-1",
            "usage": {
              "cpu": "50m",
              "memory": "100Mi"
            }
          }
        ]
      }
    },
    {
      "namespace": "kube-system",
      "name": "pod-2",
      "metrics": {
        "containers": [
          {
            "name": "container-1",
            "usage": {
              "cpu": "300m",
              "memory": "400Mi"
            }
          },
          {
            "name": "container-2",
            "usage": {
              "cpu": "150m",
              "memory": "200Mi"
            }
          }
        ]
      }
    },
    {
      "namespace": "production",
      "name": "pod-3",
      "metrics": {
        "containers": [
          {
            "name": "container-1",
            "usage": {
              "cpu": "10m",
              "memory": "20Mi"
            }
          }
        ]
      }
    }
  ]
}
